[
{
"id":"CD001",
"academy":"Aptitude",
"level":"Logical Reasoning",
"topic":"Coding-Decoding",
"subtopic":"Letter Coding",
"difficulty":"Easy",
"question":"If CAT is coded as DBU, then how is DOG coded?",
"options":["EPH","EPG","FPH","EOH"],
"correct_option":1,
"explanation":"Each letter is shifted one position forward: C→D, A→B, T→U. Similarly, D→E, O→P, G→H.",
"shortcut":"Check for a constant letter shift.",
"formula":"New Letter = Original Letter + 1",
"learning_tip":"Start by identifying whether each letter is shifted by a fixed number.",
"estimated_time":20,
"companies":["TCS","Infosys"],
"tags":["letter-coding","shift"]
},

{
"id":"CD002",
"academy":"Aptitude",
"level":"Logical Reasoning",
"topic":"Coding-Decoding",
"subtopic":"Letter Coding",
"difficulty":"Easy",
"question":"If BOOK is coded as CPPL, then how is PEN coded?",
"options":["QFO","QFN","RFO","QEO"],
"correct_option":1,
"explanation":"Each letter is shifted one position forward: P→Q, E→F, N→O.",
"shortcut":"Increase every letter by one.",
"formula":"Letter + 1",
"learning_tip":"Look for a simple alphabetical shift before trying complex patterns.",
"estimated_time":20,
"companies":["Infosys","Capgemini"],
"tags":["letter-coding"]
},

{
"id":"CD003",
"academy":"Aptitude",
"level":"Logical Reasoning",
"topic":"Coding-Decoding",
"subtopic":"Number Coding",
"difficulty":"Easy",
"question":"If A = 1, B = 2, ..., Z = 26, what is the code for BAD?",
"options":["7","8","9","10"],
"correct_option":1,
"explanation":"B=2, A=1, D=4. Total = 2+1+4 = 7.",
"shortcut":"Replace each letter with its alphabetical position.",
"formula":"Code = Sum of Letter Positions",
"learning_tip":"Memorize A=1 to Z=26 for quick solving.",
"estimated_time":20,
"companies":["TCS","Infosys"],
"tags":["number-coding","alphabet"]
},

{
"id":"CD004",
"academy":"Aptitude",
"level":"Logical Reasoning",
"topic":"Coding-Decoding",
"subtopic":"Reverse Coding",
"difficulty":"Medium",
"question":"If SKY is coded as HPB, then the coding is based on:",
"options":["+1 Shift","Reverse Alphabet","-1 Shift","Letter Swap"],
"correct_option":2,
"explanation":"S→H, K→P, Y→B using reverse alphabetical positions (A↔Z, B↔Y, ...).",
"shortcut":"Check if letters are replaced by their opposite alphabet.",
"formula":"Reverse Alphabet Mapping",
"learning_tip":"Opposite-letter coding is frequently asked in placements.",
"estimated_time":30,
"companies":["Accenture","Infosys"],
"tags":["reverse","coding"]
},

{
"id":"CD005",
"academy":"Aptitude",
"level":"Logical Reasoning",
"topic":"Coding-Decoding",
"subtopic":"Word Coding",
"difficulty":"Medium",
"question":"If APPLE is coded as ELPPA, then how is TRAIN coded?",
"options":["NIART","TRAIN","NRIAT","INART"],
"correct_option":1,
"explanation":"The word is written in reverse order.",
"shortcut":"Check whether the word is simply reversed.",
"formula":"Reverse the Word",
"learning_tip":"Always test for reversal before looking for letter shifts.",
"estimated_time":25,
"companies":["Infosys","Capgemini"],
"tags":["reverse-word"]
},

{
"id":"CD006",
"academy":"Aptitude",
"level":"Logical Reasoning",
"topic":"Coding-Decoding",
"subtopic":"Important",
"difficulty":"Hard",
"question":"If COMPUTER is coded as RFUVQNPC, then the coding pattern is:",
"options":["Reverse +1","Reverse Only","+2 Shift","-1 Shift"],
"correct_option":1,
"explanation":"The letters are written in reverse order: COMPUTER → RETUPMOC.",
"shortcut":"Try reversing the word before applying any shifts.",
"formula":"Reverse Sequence",
"learning_tip":"Many placement questions combine reversing with shifting. Always test reversal first.",
"estimated_time":40,
"companies":["TCS","Infosys","Accenture"],
"tags":["important","placement"]
},

{
"id":"CD007",
"academy":"Aptitude",
"level":"Logical Reasoning",
"topic":"Coding-Decoding",
"subtopic":"Mixed Coding",
"difficulty":"Hard",
"question":"If PEN is coded as QFO and BOOK is coded as CPPL, how is TABLE coded?",
"options":["UBCMF","UBCME","UCBMF","VBCMF"],
"correct_option":1,
"explanation":"Each letter is shifted one position forward: T→U, A→B, B→C, L→M, E→F.",
"shortcut":"Apply the same +1 shift to every letter.",
"formula":"Letter + 1",
"learning_tip":"Maintain consistency with the coding rule used in the examples.",
"estimated_time":40,
"companies":["TCS","Infosys","Accenture","Capgemini"],
"tags":["important","placement","coding"]
},

{
"id":"CD008",
"academy":"Aptitude",
"level":"Logical Reasoning",
"topic":"Coding-Decoding",
"subtopic":"Important",
"difficulty":"Hard",
"question":"If DELHI is coded as EFMIJ, then how is MUMBAI coded?",
"options":["NVNCBJ","NVNCBK","NVNCBJ","OVNCBJ"],
"correct_option":1,
"explanation":"Each letter is shifted one position forward: M→N, U→V, M→N, B→C, A→B, I→J.",
"shortcut":"Increase every letter by one alphabet.",
"formula":"Letter + 1",
"learning_tip":"This is one of the most common Coding-Decoding patterns asked in placement tests.",
"estimated_time":45,
"companies":["TCS","Infosys","Accenture","Capgemini"],
"tags":["important","placement","letter-shift"]
}
,
{
"id":"CD009",
"academy":"Aptitude",
"level":"Logical Reasoning",
"topic":"Coding-Decoding",
"subtopic":"Letter Coding",
"difficulty":"Easy",
"question":"If SUN is coded as TVO, then how is BAT coded?",
"options":["CBU","CBT","DBU","CAU"],
"correct_option":1,
"explanation":"Each letter is shifted one position forward: B→C, A→B, T→U.",
"shortcut":"Move every letter one step forward.",
"formula":"New Letter = Original Letter + 1",
"learning_tip":"Check for a uniform alphabetical shift.",
"estimated_time":20,
"companies":["TCS","Infosys"],
"tags":["letter-coding","shift"]
},

{
"id":"CD010",
"academy":"Aptitude",
"level":"Logical Reasoning",
"topic":"Coding-Decoding",
"subtopic":"Letter Coding",
"difficulty":"Easy",
"question":"If KING is coded as LJOH, then how is QUEEN coded?",
"options":["RVFFO","RVFFM","QVFFO","SVFFO"],
"correct_option":1,
"explanation":"Each letter is shifted one position forward: Q→R, U→V, E→F, E→F, N→O.",
"shortcut":"Increase every letter by one.",
"formula":"Letter + 1",
"learning_tip":"The simplest coding pattern is a fixed shift.",
"estimated_time":20,
"companies":["Infosys","Capgemini"],
"tags":["letter-coding"]
},

{
"id":"CD011",
"academy":"Aptitude",
"level":"Logical Reasoning",
"topic":"Coding-Decoding",
"subtopic":"Number Coding",
"difficulty":"Easy",
"question":"If A=1, B=2, ..., Z=26, what is the code for CAB?",
"options":["5","6","7","8"],
"correct_option":2,
"explanation":"C=3, A=1, B=2. Total = 3+1+2 = 6.",
"shortcut":"Replace letters with their positions and add.",
"formula":"Code = Sum of Alphabet Positions",
"learning_tip":"Memorize alphabetical positions for faster solving.",
"estimated_time":20,
"companies":["TCS","Infosys"],
"tags":["number-coding"]
},

{
"id":"CD012",
"academy":"Aptitude",
"level":"Logical Reasoning",
"topic":"Coding-Decoding",
"subtopic":"Reverse Coding",
"difficulty":"Medium",
"question":"If CAT is coded as XZG, then the coding pattern is:",
"options":["+1 Shift","Reverse Alphabet","Reverse Word","-1 Shift"],
"correct_option":2,
"explanation":"C→X, A→Z, T→G using opposite alphabet mapping (A↔Z, B↔Y, ...).",
"shortcut":"Check for opposite alphabet mapping.",
"formula":"Reverse Alphabet Mapping",
"learning_tip":"Opposite-letter coding is very common in reasoning tests.",
"estimated_time":30,
"companies":["Accenture","Infosys"],
"tags":["reverse-alphabet"]
},

{
"id":"CD013",
"academy":"Aptitude",
"level":"Logical Reasoning",
"topic":"Coding-Decoding",
"subtopic":"Word Coding",
"difficulty":"Medium",
"question":"If SCHOOL is coded as LOOHCS, then how is MARKET coded?",
"options":["TEKRAM","TEKRMA","TRKEMA","TEKRAM"],
"correct_option":1,
"explanation":"The word is written in reverse order. MARKET → TEKRAM.",
"shortcut":"Reverse the entire word.",
"formula":"Reverse Sequence",
"learning_tip":"Always check if the code is simply the reverse of the word.",
"estimated_time":25,
"companies":["Infosys","Capgemini"],
"tags":["reverse-word"]
},

{
"id":"CD014",
"academy":"Aptitude",
"level":"Logical Reasoning",
"topic":"Coding-Decoding",
"subtopic":"Mixed Coding",
"difficulty":"Medium",
"question":"If CAR is coded as DBS, then how is BUS coded?",
"options":["CVT","CUT","CVU","DVT"],
"correct_option":1,
"explanation":"Each letter is shifted one position forward: B→C, U→V, S→T.",
"shortcut":"Apply +1 shift to each letter.",
"formula":"Letter + 1",
"learning_tip":"Keep the coding rule consistent throughout.",
"estimated_time":30,
"companies":["TCS","Infosys"],
"tags":["mixed-coding"]
},

{
"id":"CD015",
"academy":"Aptitude",
"level":"Logical Reasoning",
"topic":"Coding-Decoding",
"subtopic":"Important",
"difficulty":"Hard",
"question":"If FLOWER is coded as GMPXFS, then how is GARDEN coded?",
"options":["HBSEFO","HBSEEM","HBRDFO","IBSEFO"],
"correct_option":1,
"explanation":"Each letter is shifted one position forward: G→H, A→B, R→S, D→E, E→F, N→O.",
"shortcut":"Increase every letter by one alphabet.",
"formula":"Letter + 1",
"learning_tip":"The +1 shift pattern is one of the most frequently asked in placement exams.",
"estimated_time":40,
"companies":["TCS","Infosys","Accenture"],
"tags":["important","placement"]
},

{
"id":"CD016",
"academy":"Aptitude",
"level":"Logical Reasoning",
"topic":"Coding-Decoding",
"subtopic":"Important",
"difficulty":"Hard",
"question":"If INDIA is coded as JOEJB, then how is CHINA coded?",
"options":["DIJOB","DIJNB","DIIOB","EHJOB"],
"correct_option":1,
"explanation":"Each letter is shifted one position forward: C→D, H→I, I→J, N→O, A→B.",
"shortcut":"Apply a +1 alphabetical shift.",
"formula":"Letter + 1",
"learning_tip":"Fixed-shift coding questions are very common in placement aptitude tests.",
"estimated_time":45,
"companies":["TCS","Infosys","Accenture","Capgemini"],
"tags":["important","placement","coding-decoding"]
},
{
"id":"CD017",
"academy":"Aptitude",
"level":"Logical Reasoning",
"topic":"Coding-Decoding",
"subtopic":"Letter Coding",
"difficulty":"Easy",
"question":"If PEN is coded as QFO, then how is MAP coded?",
"options":["NBQ","NBP","OBQ","NCP"],
"correct_option":1,
"explanation":"Each letter is shifted one position forward: M→N, A→B, P→Q.",
"shortcut":"Shift every letter one position forward.",
"formula":"New Letter = Original Letter + 1",
"learning_tip":"Look for a constant alphabetical shift.",
"estimated_time":20,
"companies":["TCS","Infosys"],
"tags":["letter-coding","shift"]
},

{
"id":"CD018",
"academy":"Aptitude",
"level":"Logical Reasoning",
"topic":"Coding-Decoding",
"subtopic":"Number Coding",
"difficulty":"Easy",
"question":"If A=1, B=2, ..., Z=26, what is the code for DOG?",
"options":["24","25","26","27"],
"correct_option":2,
"explanation":"D=4, O=15, G=7. Total = 4+15+7 = 26.",
"shortcut":"Replace each letter with its alphabetical position and add.",
"formula":"Code = Sum of Letter Positions",
"learning_tip":"Memorize A=1 to Z=26 for quick calculations.",
"estimated_time":20,
"companies":["Infosys","Capgemini"],
"tags":["number-coding"]
},

{
"id":"CD019",
"academy":"Aptitude",
"level":"Logical Reasoning",
"topic":"Coding-Decoding",
"subtopic":"Reverse Coding",
"difficulty":"Medium",
"question":"If MOON is coded as NLLO, then the coding pattern is:",
"options":["+1 Shift","-1 Shift","Reverse Word","Reverse Alphabet"],
"correct_option":2,
"explanation":"Each letter is shifted one position backward: M→L, O→N, O→N, N→M. (Pattern: -1 shift).",
"shortcut":"Check whether every letter moves backward by one.",
"formula":"New Letter = Original Letter - 1",
"learning_tip":"Test both forward and backward shifts before trying complex rules.",
"estimated_time":30,
"companies":["Accenture","Infosys"],
"tags":["reverse","letter-shift"]
},

{
"id":"CD020",
"academy":"Aptitude",
"level":"Logical Reasoning",
"topic":"Coding-Decoding",
"subtopic":"Word Coding",
"difficulty":"Medium",
"question":"If SCHOOL is coded as LOOHCS, then how is FRIEND coded?",
"options":["DNEIRF","DNERIF","DNEFRI","DENRIF"],
"correct_option":1,
"explanation":"The word is written in reverse order: FRIEND → DNEIRF.",
"shortcut":"Reverse the entire word.",
"formula":"Reverse Sequence",
"learning_tip":"Always test for word reversal before checking letter shifts.",
"estimated_time":30,
"companies":["TCS","Infosys"],
"tags":["reverse-word"]
},

{
"id":"CD021",
"academy":"Aptitude",
"level":"Logical Reasoning",
"topic":"Coding-Decoding",
"subtopic":"Mixed Coding",
"difficulty":"Medium",
"question":"If CAR is coded as DBS, then how is TRAIN coded?",
"options":["USBJO","USBJO","USBIN","VTBJO"],
"correct_option":1,
"explanation":"Each letter is shifted one position forward: T→U, R→S, A→B, I→J, N→O.",
"shortcut":"Apply a +1 shift to every letter.",
"formula":"Letter + 1",
"learning_tip":"Use the same coding rule consistently.",
"estimated_time":35,
"companies":["Infosys","Capgemini"],
"tags":["mixed-coding"]
},

{
"id":"CD022",
"academy":"Aptitude",
"level":"Logical Reasoning",
"topic":"Coding-Decoding",
"subtopic":"Important",
"difficulty":"Hard",
"question":"If APPLE is coded as BQQMF, then how is ORANGE coded?",
"options":["PSBOHF","PSBOHF","PRBOHF","PSAOHF"],
"correct_option":1,
"explanation":"Each letter is shifted one position forward: O→P, R→S, A→B, N→O, G→H, E→F.",
"shortcut":"Increase every letter by one alphabet.",
"formula":"Letter + 1",
"learning_tip":"This pattern is frequently seen in campus placement exams.",
"estimated_time":40,
"companies":["TCS","Infosys","Accenture"],
"tags":["important","placement"]
},

{
"id":"CD023",
"academy":"Aptitude",
"level":"Logical Reasoning",
"topic":"Coding-Decoding",
"subtopic":"Important",
"difficulty":"Hard",
"question":"If HOUSE is coded as IPVTF, then how is GARDEN coded?",
"options":["HBSEFO","HBSEFN","IBSEFO","HBTDFO"],
"correct_option":1,
"explanation":"Each letter is shifted one position forward: G→H, A→B, R→S, D→E, E→F, N→O.",
"shortcut":"Apply a uniform +1 shift.",
"formula":"Letter + 1",
"learning_tip":"Fixed-shift coding questions are among the most common in placement tests.",
"estimated_time":45,
"companies":["TCS","Infosys","Accenture","Capgemini"],
"tags":["important","placement","coding"]
},

{
"id":"CD024",
"academy":"Aptitude",
"level":"Logical Reasoning",
"topic":"Coding-Decoding",
"subtopic":"Important",
"difficulty":"Hard",
"question":"If DELHI is coded as EFMIJ, then how is KERALA coded?",
"options":["LFSBMB","LFSBMB","LFSBLA","MFSBMB"],
"correct_option":1,
"explanation":"Each letter is shifted one position forward: K→L, E→F, R→S, A→B, L→M, A→B.",
"shortcut":"Shift every letter one position forward.",
"formula":"Letter + 1",
"learning_tip":"Always verify that every letter follows the same coding rule.",
"estimated_time":45,
"companies":["TCS","Infosys","Accenture","Capgemini"],
"tags":["important","placement","coding-decoding"]
}
,
{
"id":"CD025",
"academy":"Aptitude",
"level":"Logical Reasoning",
"topic":"Coding-Decoding",
"subtopic":"Important",
"difficulty":"Hard",
"question":"If MOBILE is coded as NPCJMF, then how is LAPTOP coded?",
"options":[
"MBQUPQ",
"MBQUPP",
"LBQUPQ",
"MBRUQP"
],
"correct_option":1,
"explanation":"Each letter is shifted one position forward: L→M, A→B, P→Q, T→U, O→P, P→Q.",
"shortcut":"Shift every letter one position forward (+1).",
"formula":"New Letter = Original Letter + 1",
"learning_tip":"The +1 letter-shift pattern is one of the most frequently asked Coding-Decoding concepts in placement exams.",
"estimated_time":45,
"companies":[
"TCS",
"Infosys",
"Accenture",
"Capgemini",
"Cognizant",
"Wipro"
],
"tags":[
"important",
"placement",
"coding-decoding",
"letter-shift"
]
}
]