[
  {
    "id": "TR01",
    "academy": "TrippyPrep",
    "level": "Placement",
    "topic": "Geometry",
    "subtopic": "Triangles",
    "difficulty": "Easy",
    "question": "The sum of the interior angles of a triangle is:",
    "options": ["90°", "180°", "270°", "360°"],
    "correct_option": 2,
    "explanation": "The sum of the three interior angles of every triangle is always 180°.",
    "shortcut": "Triangle → 180°.",
    "formula": "∠A + ∠B + ∠C = 180°",
    "learning_tip": "This is one of the most fundamental properties of triangles.",
    "estimated_time": 20,
    "companies": ["TCS", "Infosys"],
    "tags": ["geometry", "triangles", "angles"]
  },
  {
    "id": "TR02",
    "academy": "TrippyPrep",
    "level": "Placement",
    "topic": "Geometry",
    "subtopic": "Triangles",
    "difficulty": "Easy",
    "question": "A triangle having all three sides equal is called:",
    "options": ["Scalene Triangle", "Isosceles Triangle", "Equilateral Triangle", "Right Triangle"],
    "correct_option": 3,
    "explanation": "An equilateral triangle has all three sides and all three angles equal.",
    "shortcut": "Equilateral = All equal.",
    "formula": "All sides equal",
    "learning_tip": "Each angle of an equilateral triangle measures 60°.",
    "estimated_time": 20,
    "companies": ["Wipro", "Capgemini"],
    "tags": ["geometry", "equilateral triangle"]
  },
  {
    "id": "TR03",
    "academy": "TrippyPrep",
    "level": "Placement",
    "topic": "Geometry",
    "subtopic": "Triangles",
    "difficulty": "Easy",
    "question": "A triangle having exactly two equal sides is called:",
    "options": ["Equilateral Triangle", "Scalene Triangle", "Isosceles Triangle", "Obtuse Triangle"],
    "correct_option": 3,
    "explanation": "An isosceles triangle has two equal sides and two equal base angles.",
    "shortcut": "Iso = Two equal sides.",
    "formula": "Two sides equal",
    "learning_tip": "The angles opposite the equal sides are also equal.",
    "estimated_time": 20,
    "companies": ["TCS", "HCL"],
    "tags": ["geometry", "isosceles triangle"]
  },
  {
    "id": "TR04",
    "academy": "TrippyPrep",
    "level": "Placement",
    "topic": "Geometry",
    "subtopic": "Triangles",
    "difficulty": "Easy",
    "question": "A triangle with all sides of different lengths is called:",
    "options": ["Equilateral Triangle", "Scalene Triangle", "Isosceles Triangle", "Right Triangle"],
    "correct_option": 2,
    "explanation": "A scalene triangle has no equal sides and no equal angles.",
    "shortcut": "Scalene = All different.",
    "formula": "All sides unequal",
    "learning_tip": "Every equilateral triangle is isosceles by definition, but a scalene triangle has no equal sides.",
    "estimated_time": 20,
    "companies": ["Infosys", "Cognizant"],
    "tags": ["geometry", "scalene triangle"]
  },
  {
    "id": "TR05",
    "academy": "TrippyPrep",
    "level": "Placement",
    "topic": "Geometry",
    "subtopic": "Triangles",
    "difficulty": "Medium",
    "question": "A triangle containing one angle equal to 90° is called:",
    "options": ["Acute Triangle", "Obtuse Triangle", "Right Triangle", "Scalene Triangle"],
    "correct_option": 3,
    "explanation": "A right triangle has exactly one right angle measuring 90°.",
    "shortcut": "Right angle = Right triangle.",
    "formula": "One angle = 90°",
    "learning_tip": "The side opposite the right angle is called the hypotenuse.",
    "estimated_time": 25,
    "companies": ["IBM", "Accenture"],
    "tags": ["geometry", "right triangle"]
  }
   , {
    "id": "TR06",
    "academy": "TrippyPrep",
    "level": "Placement",
    "topic": "Geometry",
    "subtopic": "Triangles",
    "difficulty": "Medium",
    "question": "A triangle with all three angles less than 90° is called:",
    "options": ["Right Triangle", "Obtuse Triangle", "Acute Triangle", "Scalene Triangle"],
    "correct_option": 3,
    "explanation": "If all three interior angles are less than 90°, the triangle is an acute triangle.",
    "shortcut": "All angles < 90° ⇒ Acute triangle.",
    "formula": "∠A < 90°, ∠B < 90°, ∠C < 90°",
    "learning_tip": "Acute triangles have no right or obtuse angles.",
    "estimated_time": 25,
    "companies": ["TCS", "Infosys"],
    "tags": ["geometry", "acute triangle"]
  },
  {
    "id": "TR07",
    "academy": "TrippyPrep",
    "level": "Placement",
    "topic": "Geometry",
    "subtopic": "Triangles",
    "difficulty": "Medium",
    "question": "A triangle with one angle greater than 90° is called:",
    "options": ["Acute Triangle", "Right Triangle", "Obtuse Triangle", "Equilateral Triangle"],
    "correct_option": 3,
    "explanation": "An obtuse triangle has one interior angle greater than 90°.",
    "shortcut": "One angle > 90° ⇒ Obtuse triangle.",
    "formula": "One angle > 90°",
    "learning_tip": "A triangle can have only one obtuse angle.",
    "estimated_time": 25,
    "companies": ["Wipro", "Capgemini"],
    "tags": ["geometry", "obtuse triangle"]
  },
  {
    "id": "TR08",
    "academy": "TrippyPrep",
    "level": "Placement",
    "topic": "Geometry",
    "subtopic": "Triangles",
    "difficulty": "Medium",
    "question": "In a right triangle, the side opposite the right angle is called:",
    "options": ["Median", "Hypotenuse", "Altitude", "Base"],
    "correct_option": 2,
    "explanation": "The hypotenuse is always the longest side and lies opposite the 90° angle.",
    "shortcut": "Opposite 90° ⇒ Hypotenuse.",
    "formula": "Hypotenuse² = Base² + Perpendicular²",
    "learning_tip": "The hypotenuse is unique to right triangles.",
    "estimated_time": 30,
    "companies": ["IBM", "Accenture"],
    "tags": ["geometry", "right triangle", "hypotenuse"]
  },
  {
    "id": "TR09",
    "academy": "TrippyPrep",
    "level": "Placement",
    "topic": "Geometry",
    "subtopic": "Triangles",
    "difficulty": "Medium",
    "question": "The Pythagorean theorem applies only to:",
    "options": ["Equilateral Triangles", "Scalene Triangles", "Right Triangles", "Isosceles Triangles"],
    "correct_option": 3,
    "explanation": "The Pythagorean theorem is valid only for right-angled triangles.",
    "shortcut": "Pythagoras ⇒ Right triangle.",
    "formula": "c² = a² + b²",
    "learning_tip": "Here, c represents the hypotenuse.",
    "estimated_time": 30,
    "companies": ["Infosys", "HCL"],
    "tags": ["geometry", "pythagoras"]
  },
  {
    "id": "TR10",
    "academy": "TrippyPrep",
    "level": "Placement",
    "topic": "Geometry",
    "subtopic": "Triangles",
    "difficulty": "Hard",
    "question": "The sides of a triangle are 3 cm, 4 cm and 5 cm. The triangle is:",
    "options": ["Equilateral", "Isosceles", "Right Triangle", "Obtuse Triangle"],
    "correct_option": 3,
    "explanation": "Since 3² + 4² = 5² (9 + 16 = 25), the triangle satisfies the Pythagorean theorem.",
    "shortcut": "Remember the 3-4-5 Pythagorean triplet.",
    "formula": "a² + b² = c²",
    "learning_tip": "3-4-5, 5-12-13 and 8-15-17 are common Pythagorean triplets.",
    "estimated_time": 35,
    "companies": ["Amazon", "Oracle"],
    "tags": ["geometry", "pythagorean triplet", "advanced"]
  },  {
    "id": "TR11",
    "academy": "TrippyPrep",
    "level": "Placement",
    "topic": "Geometry",
    "subtopic": "Triangles",
    "difficulty": "Medium",
    "question": "The angles of a triangle are in the ratio 2:3:4. Find the smallest angle.",
    "options": ["30°", "40°", "45°", "50°"],
    "correct_option": 2,
    "explanation": "Let the angles be 2x, 3x and 4x. Then 9x = 180°, so x = 20°. The smallest angle is 2x = 40°.",
    "shortcut": "Sum of angles in a triangle = 180°.",
    "formula": "∠A + ∠B + ∠C = 180°",
    "learning_tip": "Convert the ratio into algebraic expressions before solving.",
    "estimated_time": 40,
    "companies": ["TCS", "Infosys"],
    "tags": ["geometry", "triangles", "ratio"]
  },
  {
    "id": "TR12",
    "academy": "TrippyPrep",
    "level": "Placement",
    "topic": "Geometry",
    "subtopic": "Triangles",
    "difficulty": "Medium",
    "question": "The angles of a triangle are 50° and 65°. Find the third angle.",
    "options": ["55°", "60°", "65°", "75°"],
    "correct_option": 3,
    "explanation": "Third angle = 180° − (50° + 65°) = 65°.",
    "shortcut": "Subtract the sum of the known angles from 180°.",
    "formula": "Third Angle = 180° − (A + B)",
    "learning_tip": "The interior angles of every triangle always total 180°.",
    "estimated_time": 30,
    "companies": ["Wipro", "Capgemini"],
    "tags": ["geometry", "triangle angles"]
  },
  {
    "id": "TR13",
    "academy": "TrippyPrep",
    "level": "Placement",
    "topic": "Geometry",
    "subtopic": "Triangles",
    "difficulty": "Medium",
    "question": "Which of the following can form a valid triangle?",
    "options": ["2, 3, 6", "5, 5, 10", "4, 5, 6", "1, 2, 4"],
    "correct_option": 3,
    "explanation": "A triangle is valid only if the sum of any two sides is greater than the third side. Only 4, 5 and 6 satisfy this condition.",
    "shortcut": "Check whether the sum of the two smaller sides is greater than the largest side.",
    "formula": "a + b > c",
    "learning_tip": "This is known as the Triangle Inequality Theorem.",
    "estimated_time": 35,
    "companies": ["IBM", "Accenture"],
    "tags": ["geometry", "triangle inequality"]
  },
  {
    "id": "TR14",
    "academy": "TrippyPrep",
    "level": "Placement",
    "topic": "Geometry",
    "subtopic": "Triangles",
    "difficulty": "Hard",
    "question": "The sides of a triangle are 5 cm, 12 cm and 13 cm. The triangle is:",
    "options": ["Acute Triangle", "Right Triangle", "Obtuse Triangle", "Equilateral Triangle"],
    "correct_option": 2,
    "explanation": "Since 5² + 12² = 13² (25 + 144 = 169), it is a right triangle.",
    "shortcut": "Recognize the 5-12-13 Pythagorean triplet.",
    "formula": "a² + b² = c²",
    "learning_tip": "Common Pythagorean triplets appear frequently in aptitude tests.",
    "estimated_time": 40,
    "companies": ["Amazon", "Oracle"],
    "tags": ["geometry", "pythagorean triplet", "advanced"]
  },
  {
    "id": "TR15",
    "academy": "TrippyPrep",
    "level": "Placement",
    "topic": "Geometry",
    "subtopic": "Triangles",
    "difficulty": "Hard",
    "question": "In an equilateral triangle, each interior angle measures:",
    "options": ["45°", "60°", "90°", "120°"],
    "correct_option": 2,
    "explanation": "All three angles are equal and their sum is 180°. Therefore, each angle is 180° ÷ 3 = 60°.",
    "shortcut": "Equilateral triangle ⇒ 60° each.",
    "formula": "180° / 3 = 60°",
    "learning_tip": "Every equilateral triangle is also equiangular.",
    "estimated_time": 25,
    "companies": ["Microsoft", "Google"],
    "tags": ["geometry", "equilateral triangle", "advanced"]
  },
  {
    "id": "TR16",
    "academy": "TrippyPrep",
    "level": "Placement",
    "topic": "Geometry",
    "subtopic": "Triangles",
    "difficulty": "Medium",
    "question": "The sides of a triangle are 7 cm, 24 cm and 25 cm. The triangle is:",
    "options": ["Acute Triangle", "Obtuse Triangle", "Right Triangle", "Equilateral Triangle"],
    "correct_option": 3,
    "explanation": "Since 7² + 24² = 25² (49 + 576 = 625), the triangle is right-angled.",
    "shortcut": "Recognize the 7-24-25 Pythagorean triplet.",
    "formula": "a² + b² = c²",
    "learning_tip": "Memorizing common Pythagorean triplets helps solve questions quickly.",
    "estimated_time": 35,
    "companies": ["TCS", "Infosys"],
    "tags": ["geometry", "pythagorean triplet"]
  },
  {
    "id": "TR17",
    "academy": "TrippyPrep",
    "level": "Placement",
    "topic": "Geometry",
    "subtopic": "Triangles",
    "difficulty": "Medium",
    "question": "If two angles of an isosceles triangle are 70° each, the third angle is:",
    "options": ["30°", "40°", "50°", "60°"],
    "correct_option": 2,
    "explanation": "Third angle = 180° − (70° + 70°) = 40°.",
    "shortcut": "Subtract the known angles from 180°.",
    "formula": "Third Angle = 180° − (A + B)",
    "learning_tip": "The two equal angles in an isosceles triangle are called base angles.",
    "estimated_time": 30,
    "companies": ["Wipro", "Capgemini"],
    "tags": ["geometry", "isosceles triangle"]
  },
  {
    "id": "TR18",
    "academy": "TrippyPrep",
    "level": "Placement",
    "topic": "Geometry",
    "subtopic": "Triangles",
    "difficulty": "Hard",
    "question": "Which of the following side lengths cannot form a triangle?",
    "options": ["6, 8, 10", "9, 12, 15", "5, 7, 13", "8, 15, 17"],
    "correct_option": 3,
    "explanation": "For 5, 7 and 13, the sum of the two smaller sides is 12, which is less than 13. Hence, no triangle can be formed.",
    "shortcut": "Check if the sum of the two smaller sides is greater than the largest side.",
    "formula": "a + b > c",
    "learning_tip": "Triangle inequality is one of the most tested geometry concepts.",
    "estimated_time": 40,
    "companies": ["IBM", "Accenture"],
    "tags": ["geometry", "triangle inequality", "advanced"]
  },
  {
    "id": "TR19",
    "academy": "TrippyPrep",
    "level": "Placement",
    "topic": "Geometry",
    "subtopic": "Triangles",
    "difficulty": "Hard",
    "question": "The angles of a triangle are in the ratio 3:4:5. Find the largest angle.",
    "options": ["60°", "70°", "75°", "90°"],
    "correct_option": 3,
    "explanation": "Let the angles be 3x, 4x and 5x. Then 12x = 180°, so x = 15°. Largest angle = 5 × 15 = 75°.",
    "shortcut": "Convert the ratio into variables and use the angle sum property.",
    "formula": "∠A + ∠B + ∠C = 180°",
    "learning_tip": "Always divide the total angle sum by the sum of the ratio parts.",
    "estimated_time": 45,
    "companies": ["Amazon", "Oracle"],
    "tags": ["geometry", "ratio", "triangle angles"]
  },
  {
    "id": "TR20",
    "academy": "TrippyPrep",
    "level": "Placement",
    "topic": "Geometry",
    "subtopic": "Triangles",
    "difficulty": "Hard",
    "question": "A triangle has sides 8 cm, 15 cm and 17 cm. Its area is:",
    "options": ["48 cm²", "60 cm²", "64 cm²", "72 cm²"],
    "correct_option": 2,
    "explanation": "Since 8² + 15² = 17², it is a right triangle. Area = ½ × 8 × 15 = 60 cm².",
    "shortcut": "Use ½ × base × height for right triangles.",
    "formula": "Area = ½ × Base × Height",
    "learning_tip": "Recognize Pythagorean triplets to simplify area calculations.",
    "estimated_time": 50,
    "companies": ["Microsoft", "Google"],
    "tags": ["geometry", "area", "right triangle", "advanced"]
  },  {
    "id": "TR21",
    "academy": "TrippyPrep",
    "level": "Placement",
    "topic": "Geometry",
    "subtopic": "Triangles",
    "difficulty": "Hard",
    "question": "The perimeter of an equilateral triangle is 36 cm. Find the length of each side.",
    "options": ["10 cm", "11 cm", "12 cm", "13 cm"],
    "correct_option": 3,
    "explanation": "Each side = Perimeter ÷ 3 = 36 ÷ 3 = 12 cm.",
    "shortcut": "Side = Perimeter / 3.",
    "formula": "Side = Perimeter ÷ 3",
    "learning_tip": "All three sides of an equilateral triangle are equal.",
    "estimated_time": 30,
    "companies": ["TCS", "Infosys"],
    "tags": ["geometry", "equilateral triangle", "perimeter"]
  },
  {
    "id": "TR22",
    "academy": "TrippyPrep",
    "level": "Placement",
    "topic": "Geometry",
    "subtopic": "Triangles",
    "difficulty": "Hard",
    "question": "The base of a triangle is 14 cm and its height is 9 cm. Find its area.",
    "options": ["54 cm²", "63 cm²", "72 cm²", "126 cm²"],
    "correct_option": 2,
    "explanation": "Area = ½ × Base × Height = ½ × 14 × 9 = 63 cm².",
    "shortcut": "Multiply base and height, then divide by 2.",
    "formula": "Area = ½ × b × h",
    "learning_tip": "The height must be perpendicular to the base.",
    "estimated_time": 35,
    "companies": ["Wipro", "Capgemini"],
    "tags": ["geometry", "triangle area"]
  },
  {
    "id": "TR23",
    "academy": "TrippyPrep",
    "level": "Placement",
    "topic": "Geometry",
    "subtopic": "Triangles",
    "difficulty": "Hard",
    "question": "A triangle has sides 10 cm, 10 cm and 12 cm. It is:",
    "options": ["Scalene Triangle", "Right Triangle", "Isosceles Triangle", "Equilateral Triangle"],
    "correct_option": 3,
    "explanation": "Since exactly two sides are equal, the triangle is isosceles.",
    "shortcut": "Two equal sides ⇒ Isosceles triangle.",
    "formula": "Two equal sides",
    "learning_tip": "An isosceles triangle has two equal base angles.",
    "estimated_time": 30,
    "companies": ["IBM", "Accenture"],
    "tags": ["geometry", "isosceles triangle"]
  },
  {
    "id": "TR24",
    "academy": "TrippyPrep",
    "level": "Placement",
    "topic": "Geometry",
    "subtopic": "Triangles",
    "difficulty": "Hard",
    "question": "The angles of a triangle are in the ratio 5:7:8. Find the largest angle.",
    "options": ["63°", "72°", "81°", "90°"],
    "correct_option": 2,
    "explanation": "Let the angles be 5x, 7x and 8x. Then 20x = 180°, so x = 9°. Largest angle = 8 × 9 = 72°.",
    "shortcut": "Use the angle sum of 180°.",
    "formula": "∠A + ∠B + ∠C = 180°",
    "learning_tip": "Always verify your calculated value matches one of the options.",
    "estimated_time": 45,
    "companies": ["Amazon", "Oracle"],
    "tags": ["geometry", "triangle angles", "ratio", "advanced"]
  },
  {
    "id": "TR25",
    "academy": "TrippyPrep",
    "level": "Placement",
    "topic": "Geometry",
    "subtopic": "Triangles",
    "difficulty": "Hard",
    "question": "The lengths of the sides of a triangle are 9 cm, 12 cm and 15 cm. What is its perimeter?",
    "options": ["30 cm", "33 cm", "36 cm", "42 cm"],
    "correct_option": 3,
    "explanation": "Perimeter = 9 + 12 + 15 = 36 cm.",
    "shortcut": "Add all three sides.",
    "formula": "Perimeter = a + b + c",
    "learning_tip": "Always check whether the question asks for area or perimeter before solving.",
    "estimated_time": 25,
    "companies": ["Microsoft", "Google", "Deloitte"],
    "tags": ["geometry", "triangle", "perimeter", "placement"]
  }
]